odoo/addons/purchase_propagate_qty/README.rst
odoo/addons/purchase_propagate_qty/__init__.py
odoo/addons/purchase_propagate_qty/__manifest__.py
odoo/addons/purchase_propagate_qty/i18n/purchase_propagate_qty.pot
odoo/addons/purchase_propagate_qty/models/__init__.py
odoo/addons/purchase_propagate_qty/models/purchase.py
odoo/addons/purchase_propagate_qty/readme/CONTRIBUTORS.rst
odoo/addons/purchase_propagate_qty/readme/DESCRIPTION.rst
odoo/addons/purchase_propagate_qty/readme/HISTORY.rst
odoo/addons/purchase_propagate_qty/readme/USAGE.rst
odoo/addons/purchase_propagate_qty/static/description/icon.png
odoo/addons/purchase_propagate_qty/static/description/index.html
odoo/addons/purchase_propagate_qty/tests/__init__.py
odoo/addons/purchase_propagate_qty/tests/test_purchase_delivery.py
odoo12_addon_purchase_propagate_qty-12.0.1.0.0.99.dev2.dist-info/METADATA
odoo12_addon_purchase_propagate_qty-12.0.1.0.0.99.dev2.dist-info/WHEEL
odoo12_addon_purchase_propagate_qty-12.0.1.0.0.99.dev2.dist-info/top_level.txt
odoo12_addon_purchase_propagate_qty-12.0.1.0.0.99.dev2.dist-info/RECORD
